mcp_zhysfl/__init__.py
mcp_zhysfl/__main__.py
mcp_zhysfl/server.py
mcp_zhysfl-0.4.1.dist-info/METADATA
mcp_zhysfl-0.4.1.dist-info/WHEEL
mcp_zhysfl-0.4.1.dist-info/entry_points.txt
mcp_zhysfl-0.4.1.dist-info/top_level.txt
mcp_zhysfl-0.4.1.dist-info/RECORD
