Metadata-Version: 2.4
Name: mcp-zhysfl
Version: 0.4.1
Summary: Add your description here
Requires-Python: >=3.12
Requires-Dist: graphrag>=2.3.0
Requires-Dist: mcp>=1.10.1
Requires-Dist: openai>=1.93.2
Requires-Dist: python-dotenv>=1.1.1
